lidarr/__init__.py
lidarr/api_client.py
lidarr/api_response.py
lidarr/configuration.py
lidarr/exceptions.py
lidarr/py.typed
lidarr/rest.py
lidarr/api/__init__.py
lidarr/api/album_api.py
lidarr/api/album_lookup_api.py
lidarr/api/album_studio_api.py
lidarr/api/api_info_api.py
lidarr/api/artist_api.py
lidarr/api/artist_editor_api.py
lidarr/api/artist_lookup_api.py
lidarr/api/authentication_api.py
lidarr/api/auto_tagging_api.py
lidarr/api/backup_api.py
lidarr/api/blocklist_api.py
lidarr/api/calendar_api.py
lidarr/api/calendar_feed_api.py
lidarr/api/command_api.py
lidarr/api/custom_filter_api.py
lidarr/api/custom_format_api.py
lidarr/api/cutoff_api.py
lidarr/api/delay_profile_api.py
lidarr/api/disk_space_api.py
lidarr/api/download_client_api.py
lidarr/api/download_client_config_api.py
lidarr/api/file_system_api.py
lidarr/api/health_api.py
lidarr/api/history_api.py
lidarr/api/host_config_api.py
lidarr/api/import_list_api.py
lidarr/api/import_list_exclusion_api.py
lidarr/api/indexer_api.py
lidarr/api/indexer_config_api.py
lidarr/api/indexer_flag_api.py
lidarr/api/language_api.py
lidarr/api/localization_api.py
lidarr/api/log_api.py
lidarr/api/log_file_api.py
lidarr/api/manual_import_api.py
lidarr/api/media_cover_api.py
lidarr/api/media_management_config_api.py
lidarr/api/metadata_api.py
lidarr/api/metadata_profile_api.py
lidarr/api/metadata_profile_schema_api.py
lidarr/api/metadata_provider_config_api.py
lidarr/api/missing_api.py
lidarr/api/naming_config_api.py
lidarr/api/notification_api.py
lidarr/api/parse_api.py
lidarr/api/ping_api.py
lidarr/api/quality_definition_api.py
lidarr/api/quality_profile_api.py
lidarr/api/quality_profile_schema_api.py
lidarr/api/queue_action_api.py
lidarr/api/queue_api.py
lidarr/api/queue_details_api.py
lidarr/api/queue_status_api.py
lidarr/api/release_api.py
lidarr/api/release_profile_api.py
lidarr/api/release_push_api.py
lidarr/api/remote_path_mapping_api.py
lidarr/api/rename_track_api.py
lidarr/api/retag_track_api.py
lidarr-1.2.1.dist-info/licenses/LICENSE
lidarr-1.2.1.dist-info/METADATA
lidarr-1.2.1.dist-info/WHEEL
lidarr-1.2.1.dist-info/top_level.txt
lidarr-1.2.1.dist-info/RECORD
