Metadata-Version: 2.4
Name: lidarr
Version: 1.2.1
Summary: Lidarr
Home-page: 
Author: OpenAPI Generator community
Author-email: OpenAPI Generator Community <team@openapitools.org>
License-Expression: GPL-3.0
Project-URL: Repository, https://github.com/devopsarr/lidarr-py
Keywords: OpenAPI,OpenAPI-Generator,Lidarr
Requires-Python: >=3.9
License-File: LICENSE
Requires-Dist: urllib3<3.0.0,>=2.1.0
Requires-Dist: python-dateutil>=2.8.2
Requires-Dist: pydantic>=2
Requires-Dist: typing-extensions>=4.7.1
Requires-Dist: lazy-imports<2,>=1
Dynamic: author
Dynamic: license-file
